client/__init__.py
client/nextflow_tower_api_client/__init__.py
client/nextflow_tower_api_client/client.py
client/nextflow_tower_api_client/errors.py
client/nextflow_tower_api_client/py.typed
client/nextflow_tower_api_client/types.py
client/nextflow_tower_api_client/api/__init__.py
client/nextflow_tower_api_client/api/default/__init__.py
client/nextflow_tower_api_client/api/default/add_labels_to_actions.py
client/nextflow_tower_api_client/api/default/add_labels_to_pipelines.py
client/nextflow_tower_api_client/api/default/add_labels_to_workflows.py
client/nextflow_tower_api_client/api/default/apply_labels_to_actions.py
client/nextflow_tower_api_client/api/default/apply_labels_to_pipelines.py
client/nextflow_tower_api_client/api/default/apply_labels_to_workflows.py
client/nextflow_tower_api_client/api/default/cancel_workflow.py
client/nextflow_tower_api_client/api/default/create_action.py
client/nextflow_tower_api_client/api/default/create_avatar.py
client/nextflow_tower_api_client/api/default/create_credentials.py
client/nextflow_tower_api_client/api/default/create_dataset.py
client/nextflow_tower_api_client/api/default/create_label.py
client/nextflow_tower_api_client/api/default/create_organization.py
client/nextflow_tower_api_client/api/default/create_organization_member.py
client/nextflow_tower_api_client/api/default/create_organization_team.py
client/nextflow_tower_api_client/api/default/create_organization_team_member.py
client/nextflow_tower_api_client/api/default/create_pipeline.py
client/nextflow_tower_api_client/api/default/create_pipeline_secret.py
client/nextflow_tower_api_client/api/default/create_token.py
client/nextflow_tower_api_client/api/default/create_trace.py
client/nextflow_tower_api_client/api/default/create_workflow_launch.py
client/nextflow_tower_api_client/api/default/create_workflow_star.py
client/nextflow_tower_api_client/api/default/create_workspace.py
client/nextflow_tower_api_client/api/default/create_workspace_participant.py
batch_debugging-0.1.8.dist-info/METADATA
batch_debugging-0.1.8.dist-info/WHEEL
batch_debugging-0.1.8.dist-info/top_level.txt
batch_debugging-0.1.8.dist-info/RECORD
